olm/__init__.py
olm/calcite.py
olm/general.py
olm/USGS/DataRetrieval.py
olm/USGS/PhreeqcPandas.py
olm/USGS/WQXtoPandas.py
olm/USGS/__init__.py
olm/USGS/dataSlice.py
olm/USGS/loadWaterQualityData.py
olm/USGS/plots.py
olm/USGS/siteListExtraction.py
olm/loggers/CampbellToolkit.py
olm/loggers/CyclopsToolkit.py
olm/loggers/HoboToolkit.py
olm/loggers/SchlumbergerCTDToolkit.py
olm/loggers/TruBluToolkit.py
olm/loggers/WTWpHToolkit.py
olm/loggers/__init__.py
olm/loggers/loggerScripts.py
olm_karst-0.40.dist-info/LICENSE.TXT
olm_karst-0.40.dist-info/METADATA
olm_karst-0.40.dist-info/WHEEL
olm_karst-0.40.dist-info/top_level.txt
olm_karst-0.40.dist-info/RECORD
