Metadata-Version: 2.1
Name: olm-karst
Version: 0.40
Home-page: https://github.com/speleophysics/olm/
Download-URL: https://github.com/CovingtonResearchGroup/olm/archive/refs/tags/0.40.tar.gz
Author: Matthew D. Covington
Author-email: mcoving@uark.edu
License-File: LICENSE.TXT
Requires-Dist: numpy
Requires-Dist: scipy
Requires-Dist: matplotlib
Requires-Dist: pandas
Requires-Dist: lxml
Requires-Dist: xlrd
Requires-Dist: xlwt
Requires-Dist: openpyxl
Requires-Dist: requests
